{"song":{"player1":"bf","sectionLengths":[],"gfVersion":"gf-pixel","notes":[{"typeOfSection":0,"lengthInSteps":16,"sectionNotes":[],"mustHitSection":true},{"typeOfSection":0,"lengthInSteps":16,"sectionNotes":[[1846.15384615385,3,807.692307692308]],"mustHitSection":true},{"typeOfSection":0,"lengthInSteps":16,"sectionNotes":[[3692.30769230769,2,807.692307692308]],"mustHitSection":true},{"typeOfSection":0,"lengthInSteps":16,"sectionNotes":[[5538.46153846154,1,807.692307692308]],"mustHitSection":true},{"typeOfSection":0,"lengthInSteps":16,"sectionNotes":[[7384.61538461538,1,692.307692307692]],"mustHitSection":true},{"typeOfSection":0,"lengthInSteps":16,"sectionNotes":[],"mustHitSection":false},{"typeOfSection":0,"lengthInSteps":16,"sectionNotes":[[11076.9230769231,0,807.692307692308]],"mustHitSection":true},{"typeOfSection":0,"lengthInSteps":16,"sectionNotes":[[12923.0769230769,1,807.692307692308]],"mustHitSection":true},{"typeOfSection":0,"lengthInSteps":16,"sectionNotes":[[14769.2307692308,1,807.692307692308]],"mustHitSection":true},{"typeOfSection":0,"lengthInSteps":16,"sectionNotes":[[16615.3846153846,3,807.692307692308]],"mustHitSection":true},{"typeOfSection":0,"lengthInSteps":16,"sectionNotes":[[18461.5384615385,1,807.692307692308]],"mustHitSection":true},{"typeOfSection":0,"lengthInSteps":16,"sectionNotes":[],"mustHitSection":false},{"typeOfSection":0,"lengthInSteps":16,"sectionNotes":[[22153.8461538462,3,807.692307692308]],"mustHitSection":true},{"typeOfSection":0,"lengthInSteps":16,"sectionNotes":[],"mustHitSection":false},{"typeOfSection":0,"lengthInSteps":16,"sectionNotes":[[25846.1538461539,0,807.692307692308]],"mustHitSection":true},{"typeOfSection":0,"lengthInSteps":16,"sectionNotes":[],"mustHitSection":false},{"typeOfSection":0,"lengthInSteps":16,"sectionNotes":[[29538.4615384615,2,807.692307692308],[30461.5384615385,3,0],[30692.3076923077,0,0],[30923.0769230769,2,346.153846153846]],"mustHitSection":true},{"typeOfSection":0,"lengthInSteps":16,"sectionNotes":[[31384.6153846154,1,807.692307692308],[32307.6923076923,2,0],[32538.4615384615,3,0],[32769.2307692308,1,346.153846153846]],"mustHitSection":true},{"typeOfSection":0,"lengthInSteps":16,"sectionNotes":[[33230.7692307692,3,461.538461538462],[33807.6923076923,2,461.538461538462],[34384.6153846154,1,461.538461538462]],"mustHitSection":true},{"typeOfSection":0,"lengthInSteps":16,"sectionNotes":[[35076.9230769231,2,807.692307692308],[36000,3,0],[36230.7692307692,0,0],[36461.5384615385,2,346.153846153846]],"mustHitSection":true},{"typeOfSection":0,"lengthInSteps":16,"sectionNotes":[[36923.0769230769,1,807.692307692308],[37846.1538461539,2,0],[38076.9230769231,3,0],[38307.6923076923,1,346.153846153846]],"mustHitSection":true},{"typeOfSection":0,"lengthInSteps":16,"sectionNotes":[[38769.2307692308,2,346.153846153846],[39230.7692307692,1,0],[39461.5384615385,2,346.153846153846],[39923.0769230769,1,346.153846153846]],"mustHitSection":true},{"typeOfSection":0,"lengthInSteps":16,"sectionNotes":[[40615.3846153846,1,0],[40846.1538461539,1,0],[40961.5384615385,3,0],[41192.3076923077,1,0],[41423.0769230769,2,0],[41653.8461538462,2,0],[41884.6153846154,2,0],[42230.7692307692,3,0],[42000,1,0]],"mustHitSection":true},{"typeOfSection":0,"lengthInSteps":16,"sectionNotes":[[42461.5384615385,2,0],[42692.3076923077,1,346.153846153846],[43153.8461538462,3,346.153846153846],[43615.3846153846,2,346.153846153846],[44076.9230769231,1,115.384615384615]],"mustHitSection":true},{"typeOfSection":0,"lengthInSteps":16,"sectionNotes":[],"mustHitSection":false},{"typeOfSection":0,"lengthInSteps":16,"sectionNotes":[[46153.8461538461,1,346.153846153846],[46615.3846153846,2,346.153846153846],[47076.9230769231,1,346.153846153846],[47538.4615384615,2,346.153846153846]],"mustHitSection":true},{"typeOfSection":0,"lengthInSteps":16,"sectionNotes":[[48000,2,0],[48230.7692307692,2,0],[48461.5384615385,1,346.153846153846],[48923.0769230769,3,0],[49153.8461538461,3,0],[49384.6153846154,2,346.153846153846]],"mustHitSection":true},{"typeOfSection":0,"lengthInSteps":16,"sectionNotes":[[49846.1538461538,3,346.153846153846],[50307.6923076923,2,1269.23076923077]],"mustHitSection":true},{"typeOfSection":0,"lengthInSteps":16,"sectionNotes":[],"mustHitSection":false},{"typeOfSection":0,"lengthInSteps":16,"sectionNotes":[[53538.4615384615,3,807.692307692308]],"mustHitSection":true},{"typeOfSection":0,"lengthInSteps":16,"sectionNotes":[[55384.6153846154,1,807.692307692308]],"mustHitSection":true},{"typeOfSection":0,"lengthInSteps":16,"sectionNotes":[[57230.7692307692,1,807.692307692308]],"mustHitSection":true},{"typeOfSection":0,"lengthInSteps":16,"sectionNotes":[[59076.9230769231,0,0],[59307.6923076923,2,0],[59538.4615384615,0,0],[59884.6153846154,3,0],[60115.3846153846,1,0],[60346.1538461538,3,0],[60692.3076923077,1,0]],"mustHitSection":true},{"typeOfSection":0,"lengthInSteps":16,"sectionNotes":[[60923.0769230769,1,807.692307692308]],"mustHitSection":true},{"typeOfSection":0,"lengthInSteps":16,"sectionNotes":[[62769.2307692307,3,692.307692307692]],"mustHitSection":true},{"typeOfSection":0,"lengthInSteps":16,"sectionNotes":[],"mustHitSection":false},{"typeOfSection":0,"lengthInSteps":16,"sectionNotes":[[66461.5384615384,1,807.692307692308]],"mustHitSection":true},{"typeOfSection":0,"lengthInSteps":16,"sectionNotes":[[68307.6923076923,0,807.692307692308]],"mustHitSection":true},{"typeOfSection":0,"lengthInSteps":16,"sectionNotes":[[70153.8461538461,3,1730.76923076923]],"mustHitSection":true},{"typeOfSection":0,"lengthInSteps":16,"sectionNotes":[],"mustHitSection":false},{"typeOfSection":0,"lengthInSteps":16,"sectionNotes":[],"mustHitSection":true},{"lengthInSteps":16,"sectionNotes":[],"typeOfSection":0,"mustHitSection":false,"changeBPM":false,"bpm":150},{"lengthInSteps":16,"sectionNotes":[],"typeOfSection":0,"mustHitSection":true,"changeBPM":false,"bpm":150},{"lengthInSteps":16,"sectionNotes":[],"typeOfSection":0,"mustHitSection":true,"changeBPM":false,"bpm":150},{"lengthInSteps":16,"sectionNotes":[],"typeOfSection":0,"mustHitSection":false,"changeBPM":false,"bpm":150},{"lengthInSteps":16,"sectionNotes":[],"typeOfSection":0,"mustHitSection":false,"changeBPM":false,"bpm":150},{"lengthInSteps":16,"sectionNotes":[],"typeOfSection":0,"mustHitSection":false,"changeBPM":false,"bpm":150},{"lengthInSteps":16,"sectionNotes":[],"typeOfSection":0,"mustHitSection":false,"changeBPM":false,"bpm":157},{"lengthInSteps":16,"sectionNotes":[],"typeOfSection":0,"mustHitSection":true,"changeBPM":false,"bpm":150},{"lengthInSteps":16,"sectionNotes":[],"typeOfSection":0,"mustHitSection":true,"changeBPM":false,"bpm":150},{"lengthInSteps":16,"sectionNotes":[],"typeOfSection":0,"mustHitSection":true,"changeBPM":false,"bpm":150},{"lengthInSteps":16,"sectionNotes":[],"typeOfSection":0,"mustHitSection":true,"changeBPM":false,"bpm":150},{"lengthInSteps":16,"sectionNotes":[],"typeOfSection":0,"mustHitSection":false,"changeBPM":false,"bpm":150},{"lengthInSteps":16,"sectionNotes":[],"typeOfSection":0,"mustHitSection":false,"changeBPM":false,"bpm":150},{"lengthInSteps":16,"sectionNotes":[],"typeOfSection":0,"mustHitSection":false,"changeBPM":false,"bpm":150},{"lengthInSteps":16,"sectionNotes":[],"typeOfSection":0,"mustHitSection":false,"changeBPM":false,"bpm":150},{"lengthInSteps":16,"sectionNotes":[],"typeOfSection":0,"mustHitSection":true,"changeBPM":false,"bpm":150},{"lengthInSteps":16,"sectionNotes":[],"typeOfSection":0,"mustHitSection":true,"changeBPM":false,"bpm":150},{"lengthInSteps":16,"sectionNotes":[],"typeOfSection":0,"mustHitSection":true,"changeBPM":false,"bpm":150},{"lengthInSteps":16,"sectionNotes":[],"typeOfSection":0,"mustHitSection":true,"changeBPM":false,"bpm":150},{"lengthInSteps":16,"sectionNotes":[],"typeOfSection":0,"mustHitSection":true,"changeBPM":false,"bpm":150},{"lengthInSteps":16,"sectionNotes":[],"typeOfSection":0,"mustHitSection":true,"changeBPM":false,"bpm":150},{"lengthInSteps":16,"sectionNotes":[],"typeOfSection":0,"mustHitSection":true,"changeBPM":false,"bpm":150},{"sectionNotes":[],"typeOfSection":0,"lengthInSteps":16,"altAnim":false,"mustHitSection":true,"changeBPM":false,"bpm":150},{"lengthInSteps":16,"typeOfSection":0,"sectionNotes":[],"altAnim":false,"bpm":150,"changeBPM":false,"mustHitSection":true},{"lengthInSteps":16,"typeOfSection":0,"sectionNotes":[],"altAnim":false,"bpm":150,"changeBPM":false,"mustHitSection":true},{"sectionNotes":[],"typeOfSection":0,"lengthInSteps":16,"altAnim":false,"mustHitSection":true,"changeBPM":false,"bpm":150},{"lengthInSteps":16,"typeOfSection":0,"sectionNotes":[],"altAnim":false,"bpm":130,"changeBPM":false,"mustHitSection":true},{"lengthInSteps":16,"typeOfSection":0,"sectionNotes":[],"altAnim":false,"bpm":130,"changeBPM":false,"mustHitSection":true},{"lengthInSteps":16,"typeOfSection":0,"sectionNotes":[],"altAnim":false,"bpm":130,"changeBPM":false,"mustHitSection":true},{"lengthInSteps":16,"typeOfSection":0,"sectionNotes":[],"altAnim":false,"bpm":130,"changeBPM":false,"mustHitSection":true},{"lengthInSteps":16,"typeOfSection":0,"sectionNotes":[],"altAnim":false,"bpm":130,"changeBPM":false,"mustHitSection":true},{"sectionNotes":[],"typeOfSection":0,"lengthInSteps":16,"altAnim":false,"mustHitSection":true,"changeBPM":false,"bpm":130},{"lengthInSteps":16,"altAnim":false,"typeOfSection":0,"sectionNotes":[],"bpm":130,"changeBPM":false,"mustHitSection":true}],"player2":"spooky","song":"Burning","sections":0,"validScore":true,"stage":"stage","needsVoices":true,"bpm":130,"speed":1.5}}